{
  "id": "2016-03-14-038",
  "council_id": "shingi-hosho-126721",
  "round_label": 38,
  "held_on": "2016-03-14",
  "agenda": [
    "公的年金制度の持続可能性の向上を図るための国民年金法等の一部を改正する法律案について（報告）",
    "※議題については今後変更が生じる場合があります。"
  ],
  "source_url": "https://www.mhlw.go.jp/stf/shingi2/0000115414.html",
  "minutes_links": [
    {
      "title": "議事録",
      "url": "https://www.mhlw.go.jp/stf/shingi2/0000118750.html"
    }
  ],
  "materials_links": [
    {
      "title": "資料",
      "url": "https://www.mhlw.go.jp/stf/shingi2/0000116227.html"
    }
  ],
  "announcement_links": [
    {
      "title": "開催案内",
      "url": "https://www.mhlw.go.jp/stf/shingi2/0000115414.html"
    }
  ]
}
