{
  "id": "2024-12-24-012",
  "council_id": "shingi-hosho-238274",
  "round_label": 12,
  "held_on": "2024-12-24",
  "agenda": [
    "年金記録の訂正に関する事業状況",
    "（令和５年度事業状況及び令和６年度上期概況）"
  ],
  "source_url": "https://www.mhlw.go.jp/stf/newpage_47228.html",
  "minutes_links": [
    {
      "title": "議事録",
      "url": "https://www.mhlw.go.jp/stf/newpage_51517.html"
    }
  ],
  "materials_links": [
    {
      "title": "資料",
      "url": "https://www.mhlw.go.jp/stf/shingi2/newpage_00114.html"
    }
  ],
  "announcement_links": [
    {
      "title": "開催案内",
      "url": "https://www.mhlw.go.jp/stf/newpage_47228.html"
    }
  ]
}
