{
  "id": "2024-03-14-015",
  "council_id": "newpage-13873",
  "round_label": 15,
  "held_on": "2024-03-14",
  "agenda": [
    "介護DBの利用に関するガイドライン改正について",
    "提供依頼申出の個別審査",
    "その他"
  ],
  "source_url": "https://www.mhlw.go.jp/stf/newpage_38390.html",
  "minutes_links": [
    {
      "title": "議事録［PDF形式：188KB］",
      "url": "https://www.mhlw.go.jp/content/12300000/001264396.pdf"
    }
  ],
  "materials_links": [
    {
      "title": "資料",
      "url": "https://www.mhlw.go.jp/stf/shingi2/0000198094_00078.html"
    }
  ],
  "announcement_links": [
    {
      "title": "開催案内",
      "url": "https://www.mhlw.go.jp/stf/newpage_38390.html"
    }
  ]
}
