{
  "id": "2014-07-01-536",
  "council_id": "mofa-jinji-council",
  "round_label": 536,
  "held_on": "2014-07-01",
  "agenda": [
    "中南米情勢について",
    "在勤基本手当のあり方について",
    "女性が海外で活躍できる職場とするための方策",
    "名誉総領事について",
    "次回開催日の決定"
  ],
  "source_url": "https://warp.ndl.go.jp/20250207/20250202091155/https://www.mofa.go.jp/mofaj/ms/prs/page22_001306.html",
  "minutes_links": [
    {
      "title": "第536回（7月1日）",
      "url": "https://warp.ndl.go.jp/20250207/20250202091155/https://www.mofa.go.jp/mofaj/ms/prs/page22_001306.html"
    }
  ],
  "materials_links": [],
  "announcement_links": []
}
