{
  "id": "2022-09-28-630",
  "council_id": "mofa-jinji-council",
  "round_label": 630,
  "held_on": "2022-09-28",
  "agenda": [
    "我が国の軍縮・不拡散の取組について",
    "次回開催日の決定"
  ],
  "source_url": "https://warp.ndl.go.jp/20250207/20250202091155/https://www.mofa.go.jp/mofaj/ms/prs/page23_004029.html",
  "minutes_links": [
    {
      "title": "第630回（9月28日）",
      "url": "https://warp.ndl.go.jp/20250207/20250202091155/https://www.mofa.go.jp/mofaj/ms/prs/page23_004029.html"
    }
  ],
  "materials_links": [],
  "announcement_links": []
}
