{
  "id": "2010-11-26-043",
  "council_id": "shingi-hosho-126720",
  "round_label": 43,
  "held_on": "2010-11-26",
  "agenda": [
    "年金数理部会における財政検証・国家公務員共済組合、地方公務員共済組合、私立学校教職員共済制度の財政再計算結果等の聴取について",
    "その他"
  ],
  "source_url": "https://www.mhlw.go.jp/stf/shingi/2r9852000000wrm0.html",
  "minutes_links": [
    {
      "title": "議事録",
      "url": "https://www.mhlw.go.jp/stf/shingi/2r9852000001i0vc.html"
    }
  ],
  "materials_links": [
    {
      "title": "資料",
      "url": "https://www.mhlw.go.jp/stf/shingi/2r98520000010ghd.html"
    }
  ],
  "announcement_links": [
    {
      "title": "開催案内",
      "url": "https://www.mhlw.go.jp/stf/shingi/2r9852000000wrm0.html"
    }
  ]
}
