{
  "id": "2022-09-28-013",
  "council_id": "shingi-hosho-491253",
  "round_label": 13,
  "held_on": "2022-09-28",
  "agenda": [
    "関係者からのヒアリング",
    "「新・放課後子ども総合プラン」における「一体型」の推進について",
    "インクルージョンの推進について",
    "その他"
  ],
  "source_url": "https://www.mhlw.go.jp/stf/newpage_28038.html",
  "minutes_links": [
    {
      "title": "議事録［PDF形式：461KB］",
      "url": "https://www.mhlw.go.jp/content/001004503.pdf"
    }
  ],
  "materials_links": [
    {
      "title": "資料",
      "url": "https://www.mhlw.go.jp/stf/newpage_28204.html"
    }
  ],
  "announcement_links": [
    {
      "title": "開催案内",
      "url": "https://www.mhlw.go.jp/stf/newpage_28038.html"
    }
  ]
}
