{
  "id": "2001-05-18-002",
  "council_id": "social-security-council",
  "round_label": 2,
  "held_on": "2001-05-18",
  "agenda": [],
  "source_url": "https://www.mhlw.go.jp/shingi/0105/s0518-3.html",
  "minutes_links": [
    {
      "title": "議事録［TXT形式：101KB］",
      "url": "https://www.mhlw.go.jp/content/shingi___0105___txt___s0518-1.txt"
    }
  ],
  "materials_links": [
    {
      "title": "資料",
      "url": "https://www.mhlw.go.jp/shingi/0105/s0518-3.html"
    }
  ],
  "announcement_links": []
}
