{
  "id": "2008-12-12-062",
  "council_id": "shingi-hosho-126698-00022",
  "round_label": 62,
  "held_on": "2008-12-12",
  "agenda": [
    "平成21年度介護報酬改定について",
    "その他"
  ],
  "source_url": "https://www.mhlw.go.jp/shingi/2008/12/s1212-5.html",
  "minutes_links": [
    {
      "title": "議事録［TXT形式：136KB］",
      "url": "https://www.mhlw.go.jp/shingi/2008/12/txt/s1212-2.txt"
    }
  ],
  "materials_links": [
    {
      "title": "資料",
      "url": "https://www.mhlw.go.jp/shingi/2008/12/s1212-7.html"
    }
  ],
  "announcement_links": [
    {
      "title": "開催案内",
      "url": "https://www.mhlw.go.jp/shingi/2008/12/s1212-5.html"
    }
  ]
}
