{
  "id": "2004-03-16-006",
  "council_id": "social-security-council-statistics-subcommittee",
  "round_label": 6,
  "held_on": "2004-03-16",
  "agenda": [
    "中高年者の生活に関する継続調査－中高年者縦断調査（仮称）の整備の方向について",
    "疾病、傷害及び死因分類専門委員会について",
    "平成16年国民生活基礎調査について"
  ],
  "source_url": "https://www.mhlw.go.jp/stf/shingi2/0000093933.html",
  "minutes_links": [
    {
      "title": "議事録",
      "url": "https://warp.ndl.go.jp/stf/shingi2/0000095425.html"
    }
  ],
  "materials_links": [
    {
      "title": "資料",
      "url": "https://www.mhlw.go.jp/stf/shingi2/0000093933.html"
    }
  ],
  "announcement_links": []
}
